flask_collections/__init__.py
flask_collections/collection.py
flask_collections/collections/__init__.py
flask_collections/collections/api.py
flask_collections/collections/data.py
flask_collections/collections/directory.py
flask_collections-0.3.0.dist-info/WHEEL
flask_collections-0.3.0.dist-info/METADATA
flask_collections-0.3.0.dist-info/RECORD
