Metadata-Version: 2.4
Name: flask-collections
Version: 0.3.0
Summary: Static collections for Flask
Author: Maxime Bouroumeau-Fuseau
Author-email: Maxime Bouroumeau-Fuseau <maxime.bouroumeau@gmail.com>
License-Expression: MIT
Requires-Dist: flask~=3.0
Requires-Dist: markdown~=3.6
Requires-Dist: pyyaml~=6.0
Requires-Python: >=3.10
Project-URL: Repository, https://github.com/hyperflask/flask-collections
